pyotritonclient/VERSION
pyotritonclient/__init__.py
pyotritonclient/http.py
pyotritonclient/httpclient.py
pyotritonclient/pyohttpclient.py
pyotritonclient/utils.py
pyotritonclient-0.2.6.data/data/LICENSE.txt
pyotritonclient-0.2.6.dist-info/LICENSE.txt
pyotritonclient-0.2.6.dist-info/METADATA
pyotritonclient-0.2.6.dist-info/WHEEL
pyotritonclient-0.2.6.dist-info/top_level.txt
pyotritonclient-0.2.6.dist-info/RECORD
