Metadata-Version: 2.1
Name: pyotritonclient
Version: 0.2.6
Summary: A lightweight http client library for communicating with Nvidia Triton Inference Server (with Pyodide support in the browser)
Home-page: https://github.com/oeway/pyotritonclient
Author: Wei OUYANG
Author-email: oeway007@gmail.com
License: BSD
Keywords: pyodide,http,triton,tensorrt,inference,server,service,client,nvidia
Classifier: Development Status :: 5 - Production/Stable
Classifier: Intended Audience :: Developers
Classifier: Intended Audience :: Science/Research
Classifier: Intended Audience :: Information Technology
Classifier: Topic :: Scientific/Engineering
Classifier: Topic :: Scientific/Engineering :: Image Recognition
Classifier: Topic :: Scientific/Engineering :: Artificial Intelligence
Classifier: Topic :: Software Development :: Libraries
Classifier: Topic :: Utilities
Classifier: License :: OSI Approved :: BSD License
Classifier: Programming Language :: Python :: 3
Classifier: Programming Language :: Python :: 3.6
Classifier: Programming Language :: Python :: 3.7
Classifier: Programming Language :: Python :: 3.8
Classifier: Environment :: Console
Classifier: Natural Language :: English
Classifier: Operating System :: OS Independent
License-File: LICENSE.txt
Requires-Dist: six
Requires-Dist: numpy
Requires-Dist: imjoy-rpc
Requires-Dist: msgpack
Requires-Dist: requests ; platform_system != "Emscripten"
Requires-Dist: python-rapidjson (>=0.9.1) ; platform_system != "Emscripten"
Provides-Extra: imjoy
Requires-Dist: imjoy-rpc ; extra == 'imjoy'
